{
  "500165786": {
    "taken_at": "2026-07-08T22:12:03.042204+00:00",
    "stats": {
      "503092224": {
        "battles": 37281,
        "wins": 18631,
        "damage_dealt": 36183069,
        "xp": 21473527
      },
      "589413899": {
        "battles": 13581,
        "wins": 7683,
        "damage_dealt": 30730752,
        "xp": 13104381
      },
      "527928846": {
        "battles": 13305,
        "wins": 7044,
        "damage_dealt": 14365869,
        "xp": 8015045
      },
      "505969681": {
        "battles": 32807,
        "wins": 17511,
        "damage_dealt": 49602567,
        "xp": 20826857
      },
      "543221267": {
        "battles": 30394,
        "wins": 13944,
        "damage_dealt": 22460559,
        "xp": 14158632
      },
      "547863064": {
        "battles": 33722,
        "wins": 16747,
        "damage_dealt": 46071147,
        "xp": 22968635
      },
      "720657955": {
        "battles": 0,
        "wins": 0,
        "damage_dealt": 0,
        "xp": 0
      },
      "510565929": {
        "battles": 14463,
        "wins": 7091,
        "damage_dealt": 15084309,
        "xp": 9124491
      },
      "519450673": {
        "battles": 94079,
        "wins": 47606,
        "damage_dealt": 107321619,
        "xp": 52213782
      },
      "530139698": {
        "battles": 43381,
        "wins": 20614,
        "damage_dealt": 44089369,
        "xp": 26891881
      },
      "505026611": {
        "battles": 83893,
        "wins": 42224,
        "damage_dealt": 108417281,
        "xp": 46244389
      },
      "547702965": {
        "battles": 27244,
        "wins": 14735,
        "damage_dealt": 39833800,
        "xp": 19966289
      },
      "521581632": {
        "battles": 39430,
        "wins": 21136,
        "damage_dealt": 52087113,
        "xp": 25079830
      },
      "503260226": {
        "battles": 57480,
        "wins": 30304,
        "damage_dealt": 80993436,
        "xp": 42258507
      },
      "510950979": {
        "battles": 70248,
        "wins": 40717,
        "damage_dealt": 142190161,
        "xp": 61331985
      },
      "506945096": {
        "battles": 47688,
        "wins": 24625,
        "damage_dealt": 58789761,
        "xp": 29077170
      },
      "528456293": {
        "battles": 44733,
        "wins": 22997,
        "damage_dealt": 63086521,
        "xp": 26293838
      },
      "527349863": {
        "battles": 51875,
        "wins": 25785,
        "damage_dealt": 58934471,
        "xp": 32127094
      },
      "575757376": {
        "battles": 17330,
        "wins": 9571,
        "damage_dealt": 34713148,
        "xp": 14771851
      },
      "693660786": {
        "battles": 3384,
        "wins": 1992,
        "damage_dealt": 11971488,
        "xp": 3921110
      },
      "554952723": {
        "battles": 27688,
        "wins": 14109,
        "damage_dealt": 25517347,
        "xp": 17045523
      },
      "526549111": {
        "battles": 13242,
        "wins": 7055,
        "damage_dealt": 26849937,
        "xp": 11632340
      },
      "517969531": {
        "battles": 53691,
        "wins": 24259,
        "damage_dealt": 39901343,
        "xp": 25875209
      },
      "524916348": {
        "battles": 55560,
        "wins": 27488,
        "damage_dealt": 62658653,
        "xp": 36705107
      },
      "544471168": {
        "battles": 26370,
        "wins": 12375,
        "damage_dealt": 29604053,
        "xp": 15206545
      },
      "513482373": {
        "battles": 62824,
        "wins": 28766,
        "damage_dealt": 48437273,
        "xp": 33479666
      },
      "501777545": {
        "battles": 54130,
        "wins": 28507,
        "damage_dealt": 74871442,
        "xp": 39511751
      },
      "503038091": {
        "battles": 59909,
        "wins": 31693,
        "damage_dealt": 89672899,
        "xp": 43843648
      },
      "551036051": {
        "battles": 13437,
        "wins": 7034,
        "damage_dealt": 22676517,
        "xp": 9675579
      },
      "501428373": {
        "battles": 19461,
        "wins": 10171,
        "damage_dealt": 29856485,
        "xp": 15593925
      },
      "526479510": {
        "battles": 63346,
        "wins": 31278,
        "damage_dealt": 72622710,
        "xp": 41982096
      },
      "516806813": {
        "battles": 13771,
        "wins": 6866,
        "damage_dealt": 17687236,
        "xp": 9577453
      },
      "517194401": {
        "battles": 17289,
        "wins": 8837,
        "damage_dealt": 28053574,
        "xp": 10878472
      },
      "524831909": {
        "battles": 18162,
        "wins": 9176,
        "damage_dealt": 23377490,
        "xp": 10743806
      },
      "547970216": {
        "battles": 10455,
        "wins": 5327,
        "damage_dealt": 13094207,
        "xp": 7697837
      },
      "505094315": {
        "battles": 44200,
        "wins": 22281,
        "damage_dealt": 49235763,
        "xp": 27712203
      },
      "507948204": {
        "battles": 14224,
        "wins": 7074,
        "damage_dealt": 16028557,
        "xp": 7671733
      },
      "514873012": {
        "battles": 80278,
        "wins": 38434,
        "damage_dealt": 79375770,
        "xp": 41115604
      },
      "527808181": {
        "battles": 14642,
        "wins": 7363,
        "damage_dealt": 12255345,
        "xp": 6901100
      },
      "503645374": {
        "battles": 51313,
        "wins": 26449,
        "damage_dealt": 68237340,
        "xp": 35047345
      },
      "508476609": {
        "battles": 19748,
        "wins": 10527,
        "damage_dealt": 23264404,
        "xp": 11342121
      },
      "515713088": {
        "battles": 68177,
        "wins": 33535,
        "damage_dealt": 78333401,
        "xp": 44537769
      },
      "551150804": {
        "battles": 6055,
        "wins": 3007,
        "damage_dealt": 9152835,
        "xp": 4246963
      },
      "532240089": {
        "battles": 41300,
        "wins": 21338,
        "damage_dealt": 48140815,
        "xp": 25475069
      },
      "705580253": {
        "battles": 7076,
        "wins": 3982,
        "damage_dealt": 16565833,
        "xp": 6758093
      },
      "540376799": {
        "battles": 39391,
        "wins": 20318,
        "damage_dealt": 46247075,
        "xp": 27322911
      },
      "700702945": {
        "battles": 6343,
        "wins": 2989,
        "damage_dealt": 6772567,
        "xp": 4170241
      },
      "508552424": {
        "battles": 70146,
        "wins": 34130,
        "damage_dealt": 72449645,
        "xp": 42001138
      },
      "515203827": {
        "battles": 61503,
        "wins": 31418,
        "damage_dealt": 89768704,
        "xp": 39921070
      },
      "523359477": {
        "battles": 42593,
        "wins": 21333,
        "damage_dealt": 40338999,
        "xp": 23969815
      },
      "524194043": {
        "battles": 101992,
        "wins": 53499,
        "damage_dealt": 114648034,
        "xp": 69314160
      },
      "501526791": {
        "battles": 64827,
        "wins": 32089,
        "damage_dealt": 79004310,
        "xp": 41561392
      },
      "559621391": {
        "battles": 13107,
        "wins": 6241,
        "damage_dealt": 15264005,
        "xp": 8140602
      },
      "513587473": {
        "battles": 113233,
        "wins": 57060,
        "damage_dealt": 143265870,
        "xp": 78785133
      },
      "503161116": {
        "battles": 34418,
        "wins": 18457,
        "damage_dealt": 49564317,
        "xp": 22239365
      },
      "511586266": {
        "battles": 111225,
        "wins": 53848,
        "damage_dealt": 87898539,
        "xp": 65760186
      },
      "500072754": {
        "battles": 24923,
        "wins": 12770,
        "damage_dealt": 26246532,
        "xp": 14323150
      },
      "504542514": {
        "battles": 30989,
        "wins": 15930,
        "damage_dealt": 38306253,
        "xp": 17609928
      },
      "553559263": {
        "battles": 14326,
        "wins": 7729,
        "damage_dealt": 23922089,
        "xp": 11634149
      },
      "527778114": {
        "battles": 44681,
        "wins": 26924,
        "damage_dealt": 116821447,
        "xp": 42968131
      },
      "510230853": {
        "battles": 33951,
        "wins": 16826,
        "damage_dealt": 37537432,
        "xp": 21866072
      },
      "602446663": {
        "battles": 25004,
        "wins": 12228,
        "damage_dealt": 29192411,
        "xp": 16936691
      },
      "518062924": {
        "battles": 68607,
        "wins": 38575,
        "damage_dealt": 143286725,
        "xp": 61933772
      },
      "504062946": {
        "battles": 109089,
        "wins": 58416,
        "damage_dealt": 126586783,
        "xp": 73067560
      },
      "561567062": {
        "battles": 12274,
        "wins": 6709,
        "damage_dealt": 24379023,
        "xp": 10664565
      },
      "536906073": {
        "battles": 67352,
        "wins": 34011,
        "damage_dealt": 81163245,
        "xp": 44711935
      },
      "562202459": {
        "battles": 17187,
        "wins": 8700,
        "damage_dealt": 26450268,
        "xp": 12925950
      },
      "503412573": {
        "battles": 22811,
        "wins": 11829,
        "damage_dealt": 39565537,
        "xp": 16706651
      },
      "516124134": {
        "battles": 82206,
        "wins": 44330,
        "damage_dealt": 101864907,
        "xp": 60121763
      },
      "507332460": {
        "battles": 74945,
        "wins": 36736,
        "damage_dealt": 67447340,
        "xp": 44876009
      },
      "720138094": {
        "battles": 142,
        "wins": 77,
        "damage_dealt": 196902,
        "xp": 119184
      },
      "514898288": {
        "battles": 29792,
        "wins": 14692,
        "damage_dealt": 33118405,
        "xp": 15503922
      },
      "712181824": {
        "battles": 202,
        "wins": 119,
        "damage_dealt": 574907,
        "xp": 202404
      },
      "544908164": {
        "battles": 18294,
        "wins": 8990,
        "damage_dealt": 21074976,
        "xp": 11248845
      },
      "505793926": {
        "battles": 33796,
        "wins": 16519,
        "damage_dealt": 28313404,
        "xp": 16948422
      },
      "500645443": {
        "battles": 62361,
        "wins": 31878,
        "damage_dealt": 73259433,
        "xp": 43250705
      },
      "527814557": {
        "battles": 17196,
        "wins": 8456,
        "damage_dealt": 15673681,
        "xp": 8412605
      },
      "503416226": {
        "battles": 67842,
        "wins": 34113,
        "damage_dealt": 80813723,
        "xp": 44575419
      },
      "503420390": {
        "battles": 109627,
        "wins": 55463,
        "damage_dealt": 130347908,
        "xp": 74303694
      },
      "509516203": {
        "battles": 45250,
        "wins": 22995,
        "damage_dealt": 63427002,
        "xp": 26960165
      },
      "504846775": {
        "battles": 51588,
        "wins": 26162,
        "damage_dealt": 70245768,
        "xp": 35671873
      },
      "546797496": {
        "battles": 200,
        "wins": 108,
        "damage_dealt": 488861,
        "xp": 191176
      },
      "503228354": {
        "battles": 60375,
        "wins": 29408,
        "damage_dealt": 59980004,
        "xp": 34315425
      },
      "501630284": {
        "battles": 56846,
        "wins": 30198,
        "damage_dealt": 85097284,
        "xp": 41258393
      },
      "513645986": {
        "battles": 135252,
        "wins": 66860,
        "damage_dealt": 214046125,
        "xp": 92170635
      },
      "558852058": {
        "battles": 20628,
        "wins": 10742,
        "damage_dealt": 32618656,
        "xp": 15925315
      },
      "502823906": {
        "battles": 61357,
        "wins": 30707,
        "damage_dealt": 76509499,
        "xp": 41088389
      },
      "510485478": {
        "battles": 28449,
        "wins": 15050,
        "damage_dealt": 40386266,
        "xp": 18525043
      },
      "504038908": {
        "battles": 67629,
        "wins": 37520,
        "damage_dealt": 104573306,
        "xp": 44106102
      }
    }
  },
  "500135793": {
    "taken_at": "2026-07-08T22:12:06.812716+00:00",
    "stats": {
      "506976768": {
        "battles": 21816,
        "wins": 10817,
        "damage_dealt": 22890341,
        "xp": 10246522
      },
      "543634688": {
        "battles": 65594,
        "wins": 31574,
        "damage_dealt": 53089139,
        "xp": 32183072
      },
      "551701762": {
        "battles": 60921,
        "wins": 28922,
        "damage_dealt": 55148366,
        "xp": 31187700
      },
      "514611203": {
        "battles": 80977,
        "wins": 40024,
        "damage_dealt": 101268586,
        "xp": 54998902
      },
      "514675332": {
        "battles": 6892,
        "wins": 3570,
        "damage_dealt": 11168789,
        "xp": 5378743
      },
      "526961160": {
        "battles": 34134,
        "wins": 19058,
        "damage_dealt": 55949127,
        "xp": 23842105
      },
      "516342793": {
        "battles": 47633,
        "wins": 23712,
        "damage_dealt": 47689421,
        "xp": 28964203
      },
      "509352586": {
        "battles": 39601,
        "wins": 20876,
        "damage_dealt": 49363552,
        "xp": 23789609
      },
      "560365570": {
        "battles": 43663,
        "wins": 21833,
        "damage_dealt": 51382785,
        "xp": 29436681
      },
      "525735950": {
        "battles": 50081,
        "wins": 26302,
        "damage_dealt": 79970462,
        "xp": 36540951
      },
      "558554127": {
        "battles": 13590,
        "wins": 6467,
        "damage_dealt": 14033549,
        "xp": 7520360
      },
      "705526210": {
        "battles": 56,
        "wins": 35,
        "damage_dealt": 72144,
        "xp": 42603
      },
      "507106707": {
        "battles": 14776,
        "wins": 7018,
        "damage_dealt": 9923829,
        "xp": 6633549
      },
      "509495061": {
        "battles": 60730,
        "wins": 31923,
        "damage_dealt": 91569653,
        "xp": 44720839
      },
      "510512150": {
        "battles": 66127,
        "wins": 30919,
        "damage_dealt": 52337606,
        "xp": 31967660
      },
      "531319832": {
        "battles": 22353,
        "wins": 12777,
        "damage_dealt": 36958597,
        "xp": 16658281
      },
      "556883225": {
        "battles": 35452,
        "wins": 15960,
        "damage_dealt": 31190981,
        "xp": 19903697
      },
      "504200474": {
        "battles": 80228,
        "wins": 37485,
        "damage_dealt": 95662876,
        "xp": 47855813
      },
      "502204315": {
        "battles": 109873,
        "wins": 52448,
        "damage_dealt": 120996478,
        "xp": 56493402
      },
      "713009410": {
        "battles": 354,
        "wins": 208,
        "damage_dealt": 765460,
        "xp": 350791
      },
      "503381189": {
        "battles": 23170,
        "wins": 11699,
        "damage_dealt": 24439165,
        "xp": 13994536
      },
      "514150874": {
        "battles": 9945,
        "wins": 4851,
        "damage_dealt": 9065771,
        "xp": 5330137
      },
      "504482544": {
        "battles": 85127,
        "wins": 42547,
        "damage_dealt": 86986824,
        "xp": 56922671
      },
      "504569125": {
        "battles": 80807,
        "wins": 40799,
        "damage_dealt": 94144059,
        "xp": 50321660
      },
      "529235622": {
        "battles": 2301,
        "wins": 1228,
        "damage_dealt": 3004260,
        "xp": 1747614
      },
      "506956967": {
        "battles": 21280,
        "wins": 10559,
        "damage_dealt": 22875413,
        "xp": 10567021
      },
      "513763679": {
        "battles": 36892,
        "wins": 18618,
        "damage_dealt": 43587884,
        "xp": 21849277
      },
      "524612777": {
        "battles": 12833,
        "wins": 6239,
        "damage_dealt": 11565660,
        "xp": 6136737
      },
      "513367980": {
        "battles": 40889,
        "wins": 21411,
        "damage_dealt": 46103588,
        "xp": 20830251
      },
      "540785453": {
        "battles": 10010,
        "wins": 4822,
        "damage_dealt": 10258110,
        "xp": 5548410
      },
      "504936187": {
        "battles": 10693,
        "wins": 5397,
        "damage_dealt": 8497855,
        "xp": 4863514
      },
      "541948189": {
        "battles": 13701,
        "wins": 6801,
        "damage_dealt": 12330787,
        "xp": 8061349
      },
      "550728968": {
        "battles": 30899,
        "wins": 15321,
        "damage_dealt": 39393878,
        "xp": 22028732
      },
      "533972532": {
        "battles": 18926,
        "wins": 9407,
        "damage_dealt": 17202642,
        "xp": 9525028
      },
      "514521141": {
        "battles": 56726,
        "wins": 26017,
        "damage_dealt": 55900979,
        "xp": 29509845
      },
      "531813558": {
        "battles": 54976,
        "wins": 27234,
        "damage_dealt": 62716854,
        "xp": 32687351
      },
      "524985737": {
        "battles": 73533,
        "wins": 36584,
        "damage_dealt": 77924573,
        "xp": 42209810
      },
      "517129272": {
        "battles": 39222,
        "wins": 20674,
        "damage_dealt": 46762283,
        "xp": 22737939
      },
      "501778873": {
        "battles": 14549,
        "wins": 6736,
        "damage_dealt": 9956060,
        "xp": 8108674
      },
      "519153280": {
        "battles": 50973,
        "wins": 23076,
        "damage_dealt": 39484858,
        "xp": 24771740
      },
      "503138619": {
        "battles": 26184,
        "wins": 11862,
        "damage_dealt": 24121528,
        "xp": 12912393
      },
      "562162876": {
        "battles": 4519,
        "wins": 2103,
        "damage_dealt": 3705837,
        "xp": 2324075
      },
      "543701578": {
        "battles": 59898,
        "wins": 28888,
        "damage_dealt": 45561315,
        "xp": 27696649
      },
      "519963713": {
        "battles": 17555,
        "wins": 8800,
        "damage_dealt": 19382192,
        "xp": 9852783
      },
      "505047618": {
        "battles": 35712,
        "wins": 17842,
        "damage_dealt": 34734338,
        "xp": 18489008
      },
      "513780006": {
        "battles": 41805,
        "wins": 17989,
        "damage_dealt": 41585894,
        "xp": 21922345
      },
      "525452214": {
        "battles": 45694,
        "wins": 21948,
        "damage_dealt": 25229558,
        "xp": 18025961
      },
      "557510087": {
        "battles": 15221,
        "wins": 7356,
        "damage_dealt": 16136150,
        "xp": 9157554
      },
      "502673864": {
        "battles": 20749,
        "wins": 9629,
        "damage_dealt": 12192550,
        "xp": 9308292
      },
      "539316355": {
        "battles": 6216,
        "wins": 2792,
        "damage_dealt": 4822780,
        "xp": 3139885
      },
      "502703562": {
        "battles": 27454,
        "wins": 14121,
        "damage_dealt": 30059651,
        "xp": 15328235
      },
      "542523703": {
        "battles": 30582,
        "wins": 14911,
        "damage_dealt": 19705154,
        "xp": 12352045
      },
      "516474189": {
        "battles": 44115,
        "wins": 22016,
        "damage_dealt": 48254203,
        "xp": 21095868
      },
      "531947342": {
        "battles": 21171,
        "wins": 10104,
        "damage_dealt": 21342886,
        "xp": 10437507
      },
      "507081933": {
        "battles": 44501,
        "wins": 24388,
        "damage_dealt": 77617931,
        "xp": 34901339
      },
      "500263161": {
        "battles": 109775,
        "wins": 58597,
        "damage_dealt": 156675275,
        "xp": 82442630
      },
      "504847322": {
        "battles": 17811,
        "wins": 8420,
        "damage_dealt": 13409282,
        "xp": 8047973
      },
      "504424655": {
        "battles": 23910,
        "wins": 11270,
        "damage_dealt": 21659988,
        "xp": 14112774
      },
      "517046915": {
        "battles": 25739,
        "wins": 12375,
        "damage_dealt": 22161547,
        "xp": 13010630
      },
      "568651045": {
        "battles": 18395,
        "wins": 8728,
        "damage_dealt": 16830754,
        "xp": 11168961
      },
      "515639834": {
        "battles": 33407,
        "wins": 15517,
        "damage_dealt": 32199596,
        "xp": 19387634
      },
      "505073507": {
        "battles": 33578,
        "wins": 16937,
        "damage_dealt": 33685027,
        "xp": 18927414
      },
      "514952420": {
        "battles": 34425,
        "wins": 16440,
        "damage_dealt": 30029475,
        "xp": 18204877
      },
      "501173349": {
        "battles": 110285,
        "wins": 58848,
        "damage_dealt": 135893716,
        "xp": 70203280
      },
      "501443815": {
        "battles": 44934,
        "wins": 21560,
        "damage_dealt": 36256646,
        "xp": 21781610
      },
      "516430554": {
        "battles": 18508,
        "wins": 8837,
        "damage_dealt": 26183687,
        "xp": 12794075
      },
      "542750589": {
        "battles": 18724,
        "wins": 9055,
        "damage_dealt": 14120955,
        "xp": 7928792
      },
      "501193450": {
        "battles": 68554,
        "wins": 33367,
        "damage_dealt": 71682173,
        "xp": 41790331
      },
      "519682855": {
        "battles": 47051,
        "wins": 22301,
        "damage_dealt": 44009256,
        "xp": 24670228
      },
      "518781808": {
        "battles": 59364,
        "wins": 27600,
        "damage_dealt": 45751325,
        "xp": 30877417
      },
      "510292077": {
        "battles": 30982,
        "wins": 16433,
        "damage_dealt": 30190803,
        "xp": 19895770
      },
      "501370990": {
        "battles": 20459,
        "wins": 10440,
        "damage_dealt": 22607546,
        "xp": 13954404
      },
      "503274607": {
        "battles": 42551,
        "wins": 21577,
        "damage_dealt": 40201820,
        "xp": 24887454
      },
      "507652592": {
        "battles": 121174,
        "wins": 59081,
        "damage_dealt": 119528076,
        "xp": 73040167
      },
      "506860657": {
        "battles": 55555,
        "wins": 26076,
        "damage_dealt": 53582932,
        "xp": 33109546
      },
      "500549874": {
        "battles": 57886,
        "wins": 28830,
        "damage_dealt": 64991359,
        "xp": 35567829
      },
      "513336817": {
        "battles": 2488,
        "wins": 1354,
        "damage_dealt": 3295273,
        "xp": 1791824
      },
      "506744820": {
        "battles": 20165,
        "wins": 9611,
        "damage_dealt": 17909889,
        "xp": 12332400
      },
      "712569257": {
        "battles": 5411,
        "wins": 2463,
        "damage_dealt": 5737080,
        "xp": 3577015
      },
      "503261688": {
        "battles": 47870,
        "wins": 22782,
        "damage_dealt": 32457978,
        "xp": 23915421
      },
      "507493236": {
        "battles": 13827,
        "wins": 6400,
        "damage_dealt": 9226652,
        "xp": 5729324
      },
      "569404026": {
        "battles": 9736,
        "wins": 5174,
        "damage_dealt": 13059260,
        "xp": 6376609
      },
      "696772017": {
        "battles": 12200,
        "wins": 5927,
        "damage_dealt": 14136179,
        "xp": 7988311
      },
      "534472701": {
        "battles": 27704,
        "wins": 13042,
        "damage_dealt": 17059223,
        "xp": 14747638
      },
      "526753659": {
        "battles": 35796,
        "wins": 19007,
        "damage_dealt": 57037422,
        "xp": 29349667
      }
    }
  },
  "500168264": {
    "taken_at": "2026-07-08T22:12:07.757228+00:00",
    "stats": {
      "559239296": {
        "battles": 329,
        "wins": 162,
        "damage_dealt": 139533,
        "xp": 143157
      },
      "568985088": {
        "battles": 10504,
        "wins": 5193,
        "damage_dealt": 11859541,
        "xp": 7375793
      },
      "505635075": {
        "battles": 31789,
        "wins": 16158,
        "damage_dealt": 33777489,
        "xp": 17461900
      },
      "545905030": {
        "battles": 13276,
        "wins": 6743,
        "damage_dealt": 17976336,
        "xp": 8441208
      },
      "529364103": {
        "battles": 18059,
        "wins": 9129,
        "damage_dealt": 17847534,
        "xp": 9959595
      },
      "517241481": {
        "battles": 2748,
        "wins": 1364,
        "damage_dealt": 1475192,
        "xp": 949152
      },
      "513784074": {
        "battles": 21358,
        "wins": 10356,
        "damage_dealt": 15930156,
        "xp": 8978662
      },
      "523496535": {
        "battles": 22664,
        "wins": 10710,
        "damage_dealt": 17133706,
        "xp": 10531449
      },
      "568937102": {
        "battles": 33682,
        "wins": 15585,
        "damage_dealt": 30078627,
        "xp": 17142850
      },
      "503155087": {
        "battles": 51910,
        "wins": 26092,
        "damage_dealt": 70413321,
        "xp": 30445786
      },
      "502470417": {
        "battles": 28500,
        "wins": 14852,
        "damage_dealt": 40634509,
        "xp": 18713021
      },
      "514928276": {
        "battles": 8807,
        "wins": 3902,
        "damage_dealt": 4338771,
        "xp": 3695525
      },
      "547149422": {
        "battles": 11703,
        "wins": 5993,
        "damage_dealt": 14718967,
        "xp": 7282787
      },
      "502752023": {
        "battles": 22714,
        "wins": 11809,
        "damage_dealt": 30228916,
        "xp": 15378603
      },
      "501130521": {
        "battles": 29869,
        "wins": 14389,
        "damage_dealt": 28391943,
        "xp": 12752109
      },
      "503135003": {
        "battles": 49182,
        "wins": 23477,
        "damage_dealt": 69790302,
        "xp": 30315865
      },
      "502146204": {
        "battles": 22516,
        "wins": 11743,
        "damage_dealt": 26489140,
        "xp": 13119812
      },
      "503183262": {
        "battles": 23021,
        "wins": 10792,
        "damage_dealt": 20222217,
        "xp": 12044087
      },
      "541958433": {
        "battles": 7662,
        "wins": 3595,
        "damage_dealt": 6270280,
        "xp": 3892942
      },
      "500722851": {
        "battles": 23701,
        "wins": 11003,
        "damage_dealt": 16096964,
        "xp": 11676319
      },
      "595015717": {
        "battles": 92864,
        "wins": 48253,
        "damage_dealt": 134721103,
        "xp": 66544487
      },
      "516495783": {
        "battles": 19126,
        "wins": 8975,
        "damage_dealt": 20591298,
        "xp": 10836334
      },
      "546162460": {
        "battles": 17332,
        "wins": 8235,
        "damage_dealt": 13858456,
        "xp": 9635389
      },
      "505013418": {
        "battles": 1118,
        "wins": 490,
        "damage_dealt": 676972,
        "xp": 446402
      },
      "533966635": {
        "battles": 11470,
        "wins": 5629,
        "damage_dealt": 7763267,
        "xp": 5061872
      },
      "539593388": {
        "battles": 27078,
        "wins": 13314,
        "damage_dealt": 27308333,
        "xp": 14430953
      },
      "533514671": {
        "battles": 8657,
        "wins": 3844,
        "damage_dealt": 4399497,
        "xp": 2972607
      },
      "575921193": {
        "battles": 9799,
        "wins": 4610,
        "damage_dealt": 8622074,
        "xp": 5133533
      },
      "502228663": {
        "battles": 30766,
        "wins": 15383,
        "damage_dealt": 28587003,
        "xp": 14228761
      },
      "531405760": {
        "battles": 7626,
        "wins": 3807,
        "damage_dealt": 6144015,
        "xp": 3345936
      },
      "514966852": {
        "battles": 31070,
        "wins": 14805,
        "damage_dealt": 36193808,
        "xp": 19226058
      },
      "521967559": {
        "battles": 12473,
        "wins": 6384,
        "damage_dealt": 18478594,
        "xp": 9280037
      },
      "559993928": {
        "battles": 11338,
        "wins": 5530,
        "damage_dealt": 10940917,
        "xp": 5786984
      },
      "515741133": {
        "battles": 14559,
        "wins": 7398,
        "damage_dealt": 15302122,
        "xp": 7887085
      },
      "510810062": {
        "battles": 29092,
        "wins": 15605,
        "damage_dealt": 40472750,
        "xp": 20321417
      },
      "563894989": {
        "battles": 41668,
        "wins": 19792,
        "damage_dealt": 49891092,
        "xp": 28383841
      },
      "531288400": {
        "battles": 43660,
        "wins": 19710,
        "damage_dealt": 32030515,
        "xp": 19145089
      },
      "501466833": {
        "battles": 25641,
        "wins": 13082,
        "damage_dealt": 32149878,
        "xp": 17411787
      },
      "510018258": {
        "battles": 91929,
        "wins": 45549,
        "damage_dealt": 89812040,
        "xp": 57517718
      },
      "507499733": {
        "battles": 26302,
        "wins": 12650,
        "damage_dealt": 20841306,
        "xp": 13742169
      },
      "504853079": {
        "battles": 21111,
        "wins": 10775,
        "damage_dealt": 25841768,
        "xp": 14679003
      },
      "532382180": {
        "battles": 13417,
        "wins": 6265,
        "damage_dealt": 12325615,
        "xp": 7368521
      },
      "505795419": {
        "battles": 6438,
        "wins": 3125,
        "damage_dealt": 5251633,
        "xp": 3709440
      },
      "591903332": {
        "battles": 1558,
        "wins": 682,
        "damage_dealt": 762179,
        "xp": 578310
      },
      "509951584": {
        "battles": 24618,
        "wins": 12132,
        "damage_dealt": 23295160,
        "xp": 12869827
      },
      "531170018": {
        "battles": 44094,
        "wins": 20519,
        "damage_dealt": 16408724,
        "xp": 13362015
      },
      "602911203": {
        "battles": 8157,
        "wins": 4030,
        "damage_dealt": 10134319,
        "xp": 4956245
      },
      "713080004": {
        "battles": 4,
        "wins": 1,
        "damage_dealt": 9076,
        "xp": 2174
      },
      "508109542": {
        "battles": 33128,
        "wins": 15500,
        "damage_dealt": 18861250,
        "xp": 14611105
      },
      "518882385": {
        "battles": 46570,
        "wins": 23979,
        "damage_dealt": 54321463,
        "xp": 26168518
      },
      "687732622": {
        "battles": 8067,
        "wins": 3686,
        "damage_dealt": 3626500,
        "xp": 2749604
      },
      "623908457": {
        "battles": 6498,
        "wins": 2869,
        "damage_dealt": 5672834,
        "xp": 3602146
      },
      "534208295": {
        "battles": 19246,
        "wins": 9064,
        "damage_dealt": 12202474,
        "xp": 7500297
      },
      "503192172": {
        "battles": 52929,
        "wins": 24789,
        "damage_dealt": 41645327,
        "xp": 26222222
      },
      "503569902": {
        "battles": 20183,
        "wins": 10078,
        "damage_dealt": 29606552,
        "xp": 14763067
      },
      "524758770": {
        "battles": 52983,
        "wins": 26466,
        "damage_dealt": 44065573,
        "xp": 27157030
      },
      "589793012": {
        "battles": 2850,
        "wins": 1383,
        "damage_dealt": 3564275,
        "xp": 1861507
      },
      "564190377": {
        "battles": 10242,
        "wins": 4528,
        "damage_dealt": 4159174,
        "xp": 4044195
      },
      "514732412": {
        "battles": 7918,
        "wins": 3568,
        "damage_dealt": 3976368,
        "xp": 2709139
      },
      "546704170": {
        "battles": 1748,
        "wins": 805,
        "damage_dealt": 1039606,
        "xp": 668754
      },
      "673204878": {
        "battles": 21551,
        "wins": 9515,
        "damage_dealt": 21303636,
        "xp": 11983876
      },
      "702761727": {
        "battles": 419,
        "wins": 211,
        "damage_dealt": 224799,
        "xp": 200419
      }
    }
  }
}